pyeudiw/__init__.py
pyeudiw/exceptions.py
pyeudiw/credential_presentation/handler.py
pyeudiw/credential_presentation/model.py
pyeudiw/duckle_ql/attribute_mapper.py
pyeudiw/duckle_ql/credential.py
pyeudiw/duckle_ql/handler.py
pyeudiw/federation/__init__.py
pyeudiw/federation/exceptions.py
pyeudiw/federation/http_client.py
pyeudiw/federation/policy.py
pyeudiw/federation/statements.py
pyeudiw/federation/trust_chain_builder.py
pyeudiw/federation/trust_chain_validator.py
pyeudiw/federation/utils.py
pyeudiw/federation/schemas/__init__.py
pyeudiw/federation/schemas/entity_configuration.py
pyeudiw/federation/schemas/federation_configuration.py
pyeudiw/federation/schemas/federation_entity.py
pyeudiw/federation/schemas/openid_credential_verifier.py
pyeudiw/federation/trust_chain/__init__.py
pyeudiw/federation/trust_chain/builder.py
pyeudiw/federation/trust_chain/validator.py
pyeudiw/jwk/__init__.py
pyeudiw/jwk/exceptions.py
pyeudiw/jwk/jwks.py
pyeudiw/jwk/parse.py
pyeudiw/jwk/schemas/__init__.py
pyeudiw/jwk/schemas/public.py
pyeudiw/jwt/__init__.py
pyeudiw/jwt/exceptions.py
pyeudiw/jwt/helper.py
pyeudiw/jwt/jwe_helper.py
pyeudiw/jwt/jws_helper.py
pyeudiw/jwt/log.py
pyeudiw/jwt/parse.py
pyeudiw/jwt/utils.py
pyeudiw/jwt/verification.py
pyeudiw/jwt/schemas/jwt.py
pyeudiw/oauth2/__init__.py
pyeudiw/oauth2/dpop/__init__.py
pyeudiw/oauth2/dpop/exceptions.py
pyeudiw/oauth2/dpop/schema.py
pyeudiw/openid4vp/__init__.py
pyeudiw/openid4vp/authorization_request.py
pyeudiw/openid4vp/authorization_response.py
pyeudiw/openid4vp/exceptions.py
pyeudiw/openid4vp/interface.py
pyeudiw/openid4vp/utils.py
pyeudiw/openid4vp/vp.py
pyeudiw/openid4vp/vp_mdoc_cbor.py
pyeudiw/openid4vp/vp_sd_jwt_vc.py
pyeudiw/openid4vp/presentation_submission/__init__.py
pyeudiw/openid4vp/presentation_submission/base_vp_parser.py
pyeudiw/openid4vp/presentation_submission/exceptions.py
pyeudiw/openid4vp/presentation_submission/schemas.py
pyeudiw/openid4vp/schemas/__init__.py
pyeudiw/openid4vp/schemas/cnf_schema.py
pyeudiw-1.0.0.dist-info/licenses/LICENSE
pyeudiw-1.0.0.dist-info/METADATA
pyeudiw-1.0.0.dist-info/WHEEL
pyeudiw-1.0.0.dist-info/top_level.txt
pyeudiw-1.0.0.dist-info/RECORD
