Metadata-Version: 2.4
Name: pyeudiw
Version: 1.0.0
Summary: Python toolchain for building an OpenID4VP RP with a SATOSA backend compliant to the Italian Wallet Solution.
Home-page: https://github.com/italia/eudi-wallet-it-python
Author: Giuseppe De Marco
Author-email: demarcog83@gmail.com
License: License :: OSI Approved :: Apache Software License
Classifier: Development Status :: 4 - Beta
Classifier: License :: OSI Approved :: Apache Software License
Classifier: Programming Language :: Python :: 3.9
Classifier: Programming Language :: Python :: 3.10
Classifier: Programming Language :: Python :: 3.11
Classifier: Topic :: Software Development :: Libraries :: Python Modules
License-File: LICENSE
Requires-Dist: cryptojwt<1.10,>=1.9
Requires-Dist: pydantic<2.11,>=2.10
Requires-Dist: pyqrcode<1.3,>=1.2
Requires-Dist: pem<23.2,>=23.1
Dynamic: author
Dynamic: author-email
Dynamic: classifier
Dynamic: description
Dynamic: description-content-type
Dynamic: home-page
Dynamic: license
Dynamic: license-file
Dynamic: requires-dist
Dynamic: summary
